llvm_snapshot_builder/__init__.py
llvm_snapshot_builder/actions/__init__.py
llvm_snapshot_builder/actions/action.py
llvm_snapshot_builder/actions/build_all_packages.py
llvm_snapshot_builder/actions/build_packages.py
llvm_snapshot_builder/actions/cancel_builds.py
llvm_snapshot_builder/actions/create_packages.py
llvm_snapshot_builder/actions/create_project.py
llvm_snapshot_builder/actions/delete_builds.py
llvm_snapshot_builder/actions/delete_project.py
llvm_snapshot_builder/actions/fork_project.py
llvm_snapshot_builder/actions/project_exists.py
llvm_snapshot_builder/actions/regenerate_repos.py
llvm_snapshot_builder/cli.py
llvm_snapshot_builder/copr_project_ref.py
llvm_snapshot_builder/mixins/__init__.py
llvm_snapshot_builder/mixins/build_walker_mixin.py
llvm_snapshot_builder/mixins/client_mixin.py
llvm_snapshot_builder/mixins/package_builder_mixin.py
llvm_snapshot_builder-1.2.8.dist-info/METADATA
llvm_snapshot_builder-1.2.8.dist-info/entry_points.txt
llvm_snapshot_builder-1.2.8.dist-info/WHEEL
llvm_snapshot_builder-1.2.8.dist-info/LICENSE
llvm_snapshot_builder-1.2.8.dist-info/RECORD
