Metadata-Version: 2.1
Name: llvm-snapshot-builder
Version: 1.2.8
Summary: Builds LLVM snapshots on Copr
Home-page: https://pypi.org/project/llvm_snapshot_builder/
License: MIT
Keywords: LLVM,Snapshot,Copr,Fedora,Builder
Author: Konrad Kleine
Author-email: kkleine@redhat.com
Maintainer: Konrad Kleine
Maintainer-email: kkleine@redhat.com
Requires-Python: >=3.9,<4
Classifier: License :: OSI Approved :: MIT License
Classifier: Programming Language :: Python :: 3
Classifier: Programming Language :: Python :: 3.9
Classifier: Programming Language :: Python :: 3.10
Classifier: Programming Language :: Python :: 3.11
Requires-Dist: copr (>=1.124,<2.0)
Project-URL: Documentation, https://llvm_snapshot_builder.readthedocs.io/en/latest/?badge=latest
Project-URL: Repository, https://github.com/kwk/llvm_snapshot_builder/
